a_pandas_ex_old_school_for_loop/LICENSE
a_pandas_ex_old_school_for_loop/README.MD
a_pandas_ex_old_school_for_loop/__init__.py
a_pandas_ex_old_school_for_loop/requirements.txt
a_pandas_ex_old_school_for_loop/thirdparty.json
a_pandas_ex_old_school_for_loop-0.1.dist-info/LICENSE.rst
a_pandas_ex_old_school_for_loop-0.1.dist-info/METADATA
a_pandas_ex_old_school_for_loop-0.1.dist-info/WHEEL
a_pandas_ex_old_school_for_loop-0.1.dist-info/top_level.txt
a_pandas_ex_old_school_for_loop-0.1.dist-info/RECORD
