Metadata-Version: 2.1
Name: a-pandas-ex-old-school-for-loop
Version: 0.1
Summary: How about an old school inplace-for-loop for Pandas DataFrames? :)
Home-page: https://github.com/hansalemaos/a_pandas_ex_old_school_for_loop
Author: Johannes Fischer
Author-email: <aulasparticularesdealemaosp@gmail.com>
License: MIT
Keywords: list,dict,python,nested,pandas,DataFrame,Series
Classifier: Development Status :: 4 - Beta
Classifier: Programming Language :: Python :: 3 :: Only
Classifier: Programming Language :: Python :: 3.9
Classifier: Topic :: Scientific/Engineering :: Visualization
Classifier: Topic :: Software Development :: Libraries :: Python Modules
Classifier: Topic :: Text Editors :: Text Processing
Classifier: Topic :: Text Processing :: General
Classifier: Topic :: Text Processing :: Indexing
Classifier: Topic :: Text Processing :: Filters
Classifier: Topic :: Utilities
License-File: LICENSE.rst
Requires-Dist: flatten-any-dict-iterable-or-whatsoever
Requires-Dist: nestednop
Requires-Dist: pandas
Requires-Dist: useful-functions-easier-life
